jikanapi/__init__.py
jikanapi/jikan_api.py
jikanapi/models/__init__.py
jikanapi/models/anime.py
jikanapi-0.2.3.dist-info/METADATA
jikanapi-0.2.3.dist-info/WHEEL
jikanapi-0.2.3.dist-info/top_level.txt
jikanapi-0.2.3.dist-info/RECORD
