Metadata-Version: 2.1
Name: jikanapi
Version: 0.2.3
Summary: A Python wrapper for the Jikan API for MyAnimeList.
Home-page: https://github.com/praveensenpai/Jikanapi
Author: Praveen Senpai
Author-email: pvnt20@gmail.com
Requires-Python: >=3.6
Requires-Dist: jikanpy-v4>=1.0.2
Requires-Dist: pydantic>=2.9.2
Requires-Dist: rich>=13.9.3
